jt_package_name/__init__.py
jt_package_name-1.0.0.dist-info/LICENCE
jt_package_name-1.0.0.dist-info/METADATA
jt_package_name-1.0.0.dist-info/WHEEL
jt_package_name-1.0.0.dist-info/top_level.txt
jt_package_name-1.0.0.dist-info/RECORD
