Metadata-Version: 2.1
Name: jt-package-name
Version: 1.0.0
Summary: Python Package Template
Home-page: https://linkedin.com/in/joetilsed/
Author: Joe Tilsed
Author-email: Joe@Tilsed.com
License: UNKNOWN
Keywords: jt_package_name python
Platform: UNKNOWN
Classifier: Programming Language :: Python :: 3
Classifier: License :: OSI Approved :: MIT License
Classifier: Operating System :: OS Independent
